library_master/main.py
library_master/mcp_service.py
library_master/cache/__init__.py
library_master/cache/cacheout_manager.py
library_master/cache/manager.py
library_master/clients/__init__.py
library_master/clients/context7_client.py
library_master/core/__init__.py
library_master/core/config.py
library_master/core/mirror_config.py
library_master/core/processor.py
library_master/core/server.py
library_master/exceptions/__init__.py
library_master/models/__init__.py
library_master/tools/__init__.py
library_master/tools/context7_tools.py
library_master/workers/__init__.py
library_master/workers/base.py
library_master/workers/cpp_worker.py
library_master/workers/go_worker.py
library_master/workers/java_worker.py
library_master/workers/node_worker.py
library_master/workers/python_worker.py
library_master/workers/rust_worker.py
library_master-0.1.3.dist-info/METADATA
library_master-0.1.3.dist-info/WHEEL
library_master-0.1.3.dist-info/entry_points.txt
library_master-0.1.3.dist-info/RECORD
