Metadata-Version: 2.4
Name: library_master
Version: 0.1.3
Summary: Multi-language Code Package (MCP) latest version query service
Author-email: Kirky-X <kirky-x@outlook.com>
Requires-Python: >=3.10
Requires-Dist: cacheout>=0.16.0
Requires-Dist: httpx>=0.28.1
Requires-Dist: mcp>=1.13.1
Requires-Dist: pydantic-settings>=2.10.1
Requires-Dist: pydantic>=2.11.7
Requires-Dist: requests>=2.32.5
Requires-Dist: typing-extensions>=4.15.0
Provides-Extra: dev
Requires-Dist: black>=25.1.0; extra == 'dev'
Requires-Dist: mypy>=1.17.1; extra == 'dev'
Requires-Dist: pytest-asyncio>=1.1.0; extra == 'dev'
Requires-Dist: pytest-cov>=6.2.1; extra == 'dev'
Requires-Dist: pytest>=8.4.1; extra == 'dev'
Requires-Dist: ruff>=0.12.11; extra == 'dev'
